smartphone_robot_flatbuffers/AudioTimestamp.py
smartphone_robot_flatbuffers/BatteryData.py
smartphone_robot_flatbuffers/ChargerData.py
smartphone_robot_flatbuffers/CommAction.py
smartphone_robot_flatbuffers/Episode.py
smartphone_robot_flatbuffers/Image.py
smartphone_robot_flatbuffers/ImageData.py
smartphone_robot_flatbuffers/IndividualWheelData.py
smartphone_robot_flatbuffers/MotionAction.py
smartphone_robot_flatbuffers/OrientationData.py
smartphone_robot_flatbuffers/RobotAction.py
smartphone_robot_flatbuffers/SoundData.py
smartphone_robot_flatbuffers/TimeStep.py
smartphone_robot_flatbuffers/WheelData.py
smartphone_robot_flatbuffers/__init__.py
smartphone_robot_flatbuffers-0.0.2.dist-info/METADATA
smartphone_robot_flatbuffers-0.0.2.dist-info/WHEEL
smartphone_robot_flatbuffers-0.0.2.dist-info/licenses/LICENSE
smartphone_robot_flatbuffers-0.0.2.dist-info/RECORD
