Metadata-Version: 2.3
Name: smartphone_robot_flatbuffers
Version: 0.0.2
Summary: Generated flatbuffer python classes for the OIST smartphone-robot Android-2-Python API
Project-URL: Homepage, https://github.com/oist/smartphone-robot-flatbuffers
Project-URL: Issues, https://github.com/oist/smartphone-robot-flatbuffers/issues
Author-email: Christopher Buckley <topherbuckley@gmail.com>
License-File: LICENSE
Classifier: License :: OSI Approved :: MIT License
Classifier: Operating System :: OS Independent
Classifier: Programming Language :: Python :: 3
Requires-Python: >=3.8
Requires-Dist: flatbuffers==2.0
